Python3ModuleExamples/README.md
Python3ModuleExamples/__init__.py
Python3ModuleExamples/__main__.py
Python3ModuleExamples/file.epub
Python3ModuleExamples/index.html
Python3ModuleExamples/css/__init__.py
Python3ModuleExamples/css/annotations.css
Python3ModuleExamples/css/main.css
Python3ModuleExamples/css/normalize.css
Python3ModuleExamples/css/popup.css
Python3ModuleExamples/font/__init__.py
Python3ModuleExamples/font/fontello.eot
Python3ModuleExamples/font/fontello.svg
Python3ModuleExamples/font/fontello.ttf
Python3ModuleExamples/font/fontello.woff
Python3ModuleExamples/img/__init__.py
Python3ModuleExamples/img/annotator-glyph-sprite.png
Python3ModuleExamples/img/annotator-icon-sprite.png
Python3ModuleExamples/img/apple-touch-icon.png
Python3ModuleExamples/img/cancelfullscreen.png
Python3ModuleExamples/img/close.png
Python3ModuleExamples/img/fullscreen.png
Python3ModuleExamples/img/loader.gif
Python3ModuleExamples/img/menu-icon.png
Python3ModuleExamples/img/save.png
Python3ModuleExamples/img/saved.png
Python3ModuleExamples/img/settings-s.png
Python3ModuleExamples/img/settings.png
Python3ModuleExamples/img/star.png
Python3ModuleExamples/js/__init__.py
Python3ModuleExamples/js/epub.js
Python3ModuleExamples/js/epub.min.js
Python3ModuleExamples/js/epub.min.map
Python3ModuleExamples/js/hooks.min.js
Python3ModuleExamples/js/hooks.min.map
Python3ModuleExamples/js/reader.js
Python3ModuleExamples/js/reader.js.map
Python3ModuleExamples/js/reader.min.js
Python3ModuleExamples/js/reader.min.map
Python3ModuleExamples/js/hooks/__init__.py
Python3ModuleExamples/js/hooks/extensions/__init__.py
Python3ModuleExamples/js/hooks/extensions/highlight.js
Python3ModuleExamples/js/libs/__init__.py
Python3ModuleExamples/js/libs/jquery.min.js
Python3ModuleExamples/js/libs/localforage.min.js
Python3ModuleExamples/js/libs/screenfull.js
Python3ModuleExamples/js/libs/screenfull.min.js
Python3ModuleExamples/js/libs/zip.min.js
Python3ModuleExamples/js/plugins/__init__.py
python_3_module_examples-2024.3.4.0.dist-info/METADATA
python_3_module_examples-2024.3.4.0.dist-info/WHEEL
python_3_module_examples-2024.3.4.0.dist-info/entry_points.txt
python_3_module_examples-2024.3.4.0.dist-info/top_level.txt
python_3_module_examples-2024.3.4.0.dist-info/RECORD
